tex2txt/__init__.py
tex2txt/shell.py
tex2txt/tex2txt.py
tex2txt-1.7.0.dist-info/LICENSE
tex2txt-1.7.0.dist-info/METADATA
tex2txt-1.7.0.dist-info/WHEEL
tex2txt-1.7.0.dist-info/top_level.txt
tex2txt-1.7.0.dist-info/RECORD
