Metadata-Version: 2.1
Name: tex2txt
Version: 1.7.0
Summary: A flexible LaTeX filter
Home-page: https://github.com/matze-dd/Tex2txt
Author: Matthias Baumann
License: UNKNOWN
Platform: UNKNOWN
Classifier: Programming Language :: Python :: 3
Classifier: License :: OSI Approved :: GNU General Public License v3 (GPLv3)
Classifier: Operating System :: OS Independent
Classifier: Topic :: Text Processing :: Markup :: LaTeX
Classifier: Topic :: Text Processing :: Filters
